picca_bookkeeper/__init__.py
picca_bookkeeper/bookkeeper.py
picca_bookkeeper/constants.py
picca_bookkeeper/dict_utils.py
picca_bookkeeper/fake_bookkeeper.py
picca_bookkeeper/heatmap_analyses.py
picca_bookkeeper/hints.py
picca_bookkeeper/read_correlations.py
picca_bookkeeper/read_deltas.py
picca_bookkeeper/read_desi_masks.py
picca_bookkeeper/read_fits.py
picca_bookkeeper/resources/__init__.py
picca_bookkeeper/resources/catalogues/dla.yaml
picca_bookkeeper/resources/catalogues/quasar.yaml
picca_bookkeeper/resources/default_configs/.Y1v3.yaml
picca_bookkeeper/resources/default_configs/CRP23.yaml
picca_bookkeeper/resources/default_configs/Jurav1.yaml
picca_bookkeeper/resources/default_configs/TrueMocks.yaml
picca_bookkeeper/resources/default_configs/Y1v0+.yaml
picca_bookkeeper/resources/default_configs/Y1v1.yaml
picca_bookkeeper/resources/default_configs/Y1v2.yaml
picca_bookkeeper/resources/default_configs/Y1v3.yaml
picca_bookkeeper/resources/default_configs/Y1v4.yaml
picca_bookkeeper/resources/default_configs/Y1v5.yaml
picca_bookkeeper/resources/default_configs/Y1v6.yaml
picca_bookkeeper/resources/default_configs/Y1v7.yaml
picca_bookkeeper/resources/default_configs/dMdB20.yaml
picca_bookkeeper/resources/default_configs/kibo_v1.yaml
picca_bookkeeper/resources/default_configs/loa_v1.yaml
picca_bookkeeper/resources/default_configs/loa_v2.yaml
picca_bookkeeper/resources/default_configs/quickquasars.yaml
picca_bookkeeper/resources/example_config.yaml
picca_bookkeeper/resources/fit_models/PlanckDR16.fits
picca_bookkeeper/resources/fit_models/__init__.py
picca_bookkeeper/scripts/__init__.py
picca_bookkeeper/scripts/add_extra_deltas_data.py
picca_bookkeeper/scripts/add_last_night_column.py
picca_bookkeeper/scripts/cancel_jobids_from_file.py
picca_bookkeeper/scripts/compare_bookkeepers.py
picca_bookkeeper/scripts/compute_zeff.py
picca_bookkeeper/scripts/convert_deltas_format.py
picca_bookkeeper/scripts/correct_config_zeff.py
picca_bookkeeper/scripts/fix_bookkeeper_links.py
picca_bookkeeper-6.0.1.dist-info/METADATA
picca_bookkeeper-6.0.1.dist-info/WHEEL
picca_bookkeeper-6.0.1.dist-info/entry_points.txt
picca_bookkeeper-6.0.1.dist-info/RECORD
