Metadata-Version: 2.3
Name: picca_bookkeeper
Version: 6.0.1
Summary: Helper to run Lyman-α analyses using picca
Author: César Ramírez-Pérez
Requires-Python: >=3.10
Classifier: Programming Language :: Python :: 3
Classifier: Programming Language :: Python :: 3.10
Classifier: Programming Language :: Python :: 3.11
Classifier: Programming Language :: Python :: 3.12
Classifier: Programming Language :: Python :: 3.13
Requires-Dist: astropy (>=6.1.6,<7.0.0)
Requires-Dist: fitsio (>=1.2.4,<2.0.0)
Requires-Dist: getdist (>=1.5.4,<2.0.0)
Requires-Dist: healpy (>=1.18.0,<2.0.0)
Requires-Dist: importlib-resources (>=6.4.5,<7.0.0)
Requires-Dist: matplotlib (>=3.9.2,<4.0.0)
Requires-Dist: numpy (>=1.22,<2.1)
Requires-Dist: pandas (>=2.2.3,<3.0.0)
Requires-Dist: scipy (>=1.14.1,<2.0.0)
Requires-Dist: tabulate (>=0.9.0,<0.10.0)
Project-URL: Repository, https://github.com/cramirezpe/picca_bookkeeper
